kaftools/__init__.py
kaftools/filters.py
kaftools/kernels.py
kaftools/sparsifiers.py
kaftools/unittests/__init__.py
kaftools/unittests/kernel_test.py
kaftools/utils/__init__.py
kaftools/utils/data.py
kaftools/utils/shortcuts.py
kaftools-0.1.1.dist-info/DESCRIPTION.rst
kaftools-0.1.1.dist-info/METADATA
kaftools-0.1.1.dist-info/RECORD
kaftools-0.1.1.dist-info/WHEEL
kaftools-0.1.1.dist-info/metadata.json
kaftools-0.1.1.dist-info/top_level.txt
