Metadata-Version: 2.0
Name: kaftools
Version: 0.1.1
Summary: Small extensible package for Kernel Adaptive Filtering (KAF) methods.
Home-page: https://github.com/canas/kaftools
Author: Cristóbal Silva
Author-email: crsilva@ing.uchile.cl
License: MIT
Keywords: kernel adaptive filters kaf
Platform: UNKNOWN
Classifier: Development Status :: 3 - Alpha
Classifier: Intended Audience :: Science/Research
Classifier: Topic :: Scientific/Engineering :: Mathematics
Classifier: License :: OSI Approved :: MIT License
Classifier: Programming Language :: Python :: 3
Classifier: Programming Language :: Python :: 3.4
Classifier: Programming Language :: Python :: 3.5
Classifier: Programming Language :: Python :: 3.6
Requires-Dist: matplotlib
Requires-Dist: numpy
Requires-Dist: scipy
